setup.py
mpute/__init__.py
mpute/__version__.py
mpute/customThread.py
mpute/daskIterativeFAMD.py
mpute/generator.py
mpute/iterativeFAMD.py
ml_impute-0.0.7.dist-info/METADATA
ml_impute-0.0.7.dist-info/WHEEL
ml_impute-0.0.7.dist-info/licenses/LICENSE
ml_impute-0.0.7.dist-info/RECORD
