Metadata-Version: 2.1
Name: ml-impute
Version: 0.0.7
Summary: A package for synthetic data generation for imputation using single and multiple imputation methods.
Project-URL: Homepage, https://github.com/JoshWeiner/ml-impute
Project-URL: Bug Tracker, https://github.com/JoshWeiner/ml-impute/issues
Author-email: Joshua Weiner <joshuaweinernyc@gmail.com>
License: MIT License
License-File: LICENSE
Requires-Python: >=3.6
Requires-Dist: dask
Requires-Dist: jax
Requires-Dist: jaxlib
Requires-Dist: numpy
Requires-Dist: pandas
Requires-Dist: tqdm
